{"t": "D.C. Law 16-51. District Department of the Environment Establishment Act of 2005.", "p": "/us/dc/council/laws/16-51", "et": "document", "sc": "D.C. Law 16-51", "rd": "D.C. Law 16-51", "ei": "us/dc/docs/dclaw", "sp": "library|dclaws|16|D.C. Law 16-51", "sd": true, "xp": "/us/dc/council/periods/16/laws/16-51.xml", "c": [{"t": "TITLE I. GENERAL", "p": "/us/dc/council/laws/16-51#/titles/I", "et": "container", "sc": "title I", "rp": "I", "sp": "library|dclaws|16|D.C. Law 16-51|I", "c": [{"t": "\u00a7 101.", "p": "/us/dc/council/laws/16-51#\u00a7101", "et": "section", "sc": "\u00a7 101", "rp": "\u00a7101", "sp": "library|dclaws|16|D.C. Law 16-51|I|101"}, {"t": "\u00a7 102.", "p": "/us/dc/council/laws/16-51#\u00a7102", "et": "section", "sc": "\u00a7 102", "rp": "\u00a7102", "sp": "library|dclaws|16|D.C. Law 16-51|I|102"}, {"t": "\u00a7 103.", "p": "/us/dc/council/laws/16-51#\u00a7103", "et": "section", "sc": "\u00a7 103", "rp": "\u00a7103", "sp": "library|dclaws|16|D.C. Law 16-51|I|103"}, {"t": "\u00a7 104.", "p": "/us/dc/council/laws/16-51#\u00a7104", "et": "section", "sc": "\u00a7 104", "rp": "\u00a7104", "sp": "library|dclaws|16|D.C. Law 16-51|I|104"}, {"t": "\u00a7 105.", "p": "/us/dc/council/laws/16-51#\u00a7105", "et": "section", "sc": "\u00a7 105", "rp": "\u00a7105", "sp": "library|dclaws|16|D.C. Law 16-51|I|105"}, {"t": "\u00a7 106.", "p": "/us/dc/council/laws/16-51#\u00a7106", "et": "section", "sc": "\u00a7 106", "rp": "\u00a7106", "sp": "library|dclaws|16|D.C. Law 16-51|I|106"}, {"t": "\u00a7 107.", "p": "/us/dc/council/laws/16-51#\u00a7107", "et": "section", "sc": "\u00a7 107", "rp": "\u00a7107", "sp": "library|dclaws|16|D.C. Law 16-51|I|107"}, {"t": "\u00a7 108.", "p": "/us/dc/council/laws/16-51#\u00a7108", "et": "section", "sc": "\u00a7 108", "rp": "\u00a7108", "sp": "library|dclaws|16|D.C. Law 16-51|I|108"}, {"t": "\u00a7 109.", "p": "/us/dc/council/laws/16-51#\u00a7109", "et": "section", "sc": "\u00a7 109", "rp": "\u00a7109", "sp": "library|dclaws|16|D.C. Law 16-51|I|109"}, {"t": "\u00a7 110.", "p": "/us/dc/council/laws/16-51#\u00a7110", "et": "section", "sc": "\u00a7 110", "rp": "\u00a7110", "sp": "library|dclaws|16|D.C. Law 16-51|I|110"}, {"t": "\u00a7 111.", "p": "/us/dc/council/laws/16-51#\u00a7111", "et": "section", "sc": "\u00a7 111", "rp": "\u00a7111", "sp": "library|dclaws|16|D.C. Law 16-51|I|111"}, {"t": "\u00a7 112.", "p": "/us/dc/council/laws/16-51#\u00a7112", "et": "section", "sc": "\u00a7 112", "rp": "\u00a7112", "sp": "library|dclaws|16|D.C. Law 16-51|I|112"}, {"t": "\u00a7 113.", "p": "/us/dc/council/laws/16-51#\u00a7113", "et": "section", "sc": "\u00a7 113", "rp": "\u00a7113", "sp": "library|dclaws|16|D.C. Law 16-51|I|113"}, {"t": "\u00a7 114.", "p": "/us/dc/council/laws/16-51#\u00a7114", "et": "section", "sc": "\u00a7 114", "rp": "\u00a7114", "sp": "library|dclaws|16|D.C. Law 16-51|I|114"}, {"t": "\u00a7 115.", "p": "/us/dc/council/laws/16-51#\u00a7115", "et": "section", "sc": "\u00a7 115", "rp": "\u00a7115", "sp": "library|dclaws|16|D.C. Law 16-51|I|115"}]}, {"t": "TITLE I-A. STORMWATER MANAGEMENT", "p": "/us/dc/council/laws/16-51#/titles/I-A", "et": "container", "sc": "title I-A", "rp": "I-A", "sp": "library|dclaws|16|D.C. Law 16-51|I-A", "c": [{"t": "\u00a7 151.", "p": "/us/dc/council/laws/16-51#\u00a7151", "et": "section", "sc": "\u00a7 151", "rp": "\u00a7151", "sp": "library|dclaws|16|D.C. Law 16-51|I-A|151"}, {"t": "\u00a7 152.", "p": "/us/dc/council/laws/16-51#\u00a7152", "et": "section", "sc": "\u00a7 152", "rp": "\u00a7152", "sp": "library|dclaws|16|D.C. Law 16-51|I-A|152"}, {"t": "\u00a7 153.", "p": "/us/dc/council/laws/16-51#\u00a7153", "et": "section", "sc": "\u00a7 153", "rp": "\u00a7153", "sp": "library|dclaws|16|D.C. Law 16-51|I-A|153"}, {"t": "\u00a7 154.", "p": "/us/dc/council/laws/16-51#\u00a7154", "et": "section", "sc": "\u00a7 154", "rp": "\u00a7154", "sp": "library|dclaws|16|D.C. Law 16-51|I-A|154"}, {"t": "\u00a7 155.", "p": "/us/dc/council/laws/16-51#\u00a7155", "et": "section", "sc": "\u00a7 155", "rp": "\u00a7155", "sp": "library|dclaws|16|D.C. Law 16-51|I-A|155"}]}, {"t": "TITLE I-B. PRODUCT LIMITATION OF STORMWATER MANAGEMENT", "p": "/us/dc/council/laws/16-51#/titles/I-B", "et": "container", "sc": "title I-B", "rp": "I-B", "sp": "library|dclaws|16|D.C. Law 16-51|I-B", "c": [{"t": "\u00a7 181.", "p": "/us/dc/council/laws/16-51#\u00a7181", "et": "section", "sc": "\u00a7 181", "rp": "\u00a7181", "sp": "library|dclaws|16|D.C. Law 16-51|I-B|181"}]}]}